github_mcp_server_wrapper.py
github_mcp_server_wrapper-0.1.0.dist-info/METADATA
github_mcp_server_wrapper-0.1.0.dist-info/WHEEL
github_mcp_server_wrapper-0.1.0.dist-info/entry_points.txt
github_mcp_server_wrapper-0.1.0.dist-info/top_level.txt
github_mcp_server_wrapper-0.1.0.dist-info/RECORD
