Metadata-Version: 2.4
Name: github-mcp-server-wrapper
Version: 0.1.0
Summary: Python wrapper to install and run github-mcp-server Go binary via uvx
Author-email: Your Name <your.email@example.com>
License: MIT
Project-URL: Homepage, https://github.com/yourusername/github-mcp-server-wrapper
Project-URL: Bug Tracker, https://github.com/yourusername/github-mcp-server-wrapper/issues
Classifier: Development Status :: 3 - Alpha
Classifier: Intended Audience :: Developers
Classifier: License :: OSI Approved :: MIT License
Classifier: Programming Language :: Python :: 3
Classifier: Programming Language :: Python :: 3.8
Classifier: Programming Language :: Python :: 3.9
Classifier: Programming Language :: Python :: 3.10
Classifier: Programming Language :: Python :: 3.11
Classifier: Programming Language :: Python :: 3.12
Requires-Python: >=3.8
